setup.py
farbox_lite/__init__.py
farbox_lite.egg-info/PKG-INFO
farbox_lite.egg-info/SOURCES.txt
farbox_lite.egg-info/dependency_links.txt
farbox_lite.egg-info/requires.txt
farbox_lite.egg-info/top_level.txt
farbox_lite/build/__init__.py
farbox_lite/build/compile_templates.py
farbox_lite/build/css.py
farbox_lite/build/jade2jinja.py
farbox_lite/compiler/__init__.py
farbox_lite/compiler/category.py
farbox_lite/compiler/files.py
farbox_lite/compiler/site.py
farbox_lite/compiler/templates.py
farbox_lite/compiler/utils.py
farbox_lite/compiler/posts/__init__.py
farbox_lite/compiler/posts/post.py
farbox_lite/compiler/posts/posts.py
farbox_lite/render/__init__.py
farbox_lite/render/route_view.py
farbox_lite/render/web_app.py
farbox_lite/render/web_server_app.py
farbox_lite/render/apis/__init__.py
farbox_lite/render/apis/all_docs.py
farbox_lite/render/apis/data.py
farbox_lite/render/apis/files.py
farbox_lite/render/apis/posts.py
farbox_lite/render/apis/site.py
farbox_lite/render/apis/utils.py
farbox_lite/render/utils/__init__.py
farbox_lite/render/utils/render.py
farbox_lite/render/utils/api_templates/__init__.py
farbox_lite/render/utils/api_templates/paginator.py
farbox_lite/template_system/__init__.py
farbox_lite/template_system/env.py
farbox_lite/template_system/func.py
farbox_lite/template_system/utils.py
farbox_lite/template_system/app_functions/__init__.py
farbox_lite/template_system/app_functions/utils.py
farbox_lite/template_system/app_functions/after_request/__init__.py
farbox_lite/template_system/app_functions/after_request/cookie_handler.py
farbox_lite/template_system/app_functions/ba_request/__init__.py
farbox_lite/template_system/app_functions/ba_request/time_cost.py
farbox_lite/template_system/app_functions/before_request/__init__.py
farbox_lite/template_system/app_functions/before_request/basic.py
farbox_lite/template_system/functions/__init__.py
farbox_lite/template_system/functions/attr_patches/__init__.py
farbox_lite/template_system/functions/attr_patches/all.py
farbox_lite/template_system/functions/attr_patches/array.py
farbox_lite/template_system/functions/attr_patches/date.py
