Metadata-Version: 1.0
Name: farbox-lite
Version: 0.135
Summary: FarBox Lite Version
Home-page: UNKNOWN
Author: Hepochen
Author-email: hepochen@gmail.com
License: GPL
Platform: linux
